[
  {
    "college_id": "ss_armed_forces_medical_college_pune_maharashtra",
    "college_name": "Armed Forces Medical College, Pune",
    "college_type": "Government",
    "state": "Maharashtra",
    "course": "M.Ch - Plastic & Reconstructive Surgery",
    "counseling_route": "MCC",
    "quota_type": "All India Basis",
    "seats": 3,
    "seats_prev": 3,
    "seats_inc": 0
  },
  {
    "college_id": "ss_armed_forces_medical_college_pune_maharashtra",
    "college_name": "Armed Forces Medical College, Pune",
    "college_type": "Government",
    "state": "Maharashtra",
    "course": "M.Ch - Neuro Surgery",
    "counseling_route": "MCC",
    "quota_type": "All India Basis",
    "seats": 3,
    "seats_prev": 3,
    "seats_inc": 0
  },
  {
    "college_id": "ss_armed_forces_medical_college_pune_maharashtra",
    "college_name": "Armed Forces Medical College, Pune",
    "college_type": "Government",
    "state": "Maharashtra",
    "course": "M.Ch - Cardiovascular & Thoracic Surgery",
    "counseling_route": "MCC",
    "quota_type": "All India Basis",
    "seats": 3,
    "seats_prev": 3,
    "seats_inc": 0
  },
  {
    "college_id": "ss_armed_forces_medical_college_pune_maharashtra",
    "college_name": "Armed Forces Medical College, Pune",
    "college_type": "Government",
    "state": "Maharashtra",
    "course": "DM - Cardiology",
    "counseling_route": "MCC",
    "quota_type": "All India Basis",
    "seats": 1,
    "seats_prev": 1,
    "seats_inc": 0
  },
  {
    "college_id": "ss_b_j_government_medical_college_pune_maharashtra",
    "college_name": "B. J. Government Medical College, Pune",
    "college_type": "Government",
    "state": "Maharashtra",
    "course": "DM - Interventional Radiology",
    "counseling_route": "MCC",
    "quota_type": "All India Basis",
    "seats": 2,
    "seats_prev": 2,
    "seats_inc": 0
  },
  {
    "college_id": "ss_b_j_government_medical_college_pune_maharashtra",
    "college_name": "B. J. Government Medical College, Pune",
    "college_type": "Government",
    "state": "Maharashtra",
    "course": "DM - Neonatology",
    "counseling_route": "MCC",
    "quota_type": "All India Basis",
    "seats": 2,
    "seats_prev": 2,
    "seats_inc": 0
  },
  {
    "college_id": "ss_b_j_government_medical_college_pune_maharashtra",
    "college_name": "B. J. Government Medical College, Pune",
    "college_type": "Government",
    "state": "Maharashtra",
    "course": "M.Ch - Neuro Surgery",
    "counseling_route": "MCC",
    "quota_type": "All India Basis",
    "seats": 2,
    "seats_prev": 2,
    "seats_inc": 0
  },
  {
    "college_id": "ss_b_j_government_medical_college_pune_maharashtra",
    "college_name": "B. J. Government Medical College, Pune",
    "college_type": "Government",
    "state": "Maharashtra",
    "course": "M.Ch - Plastic & Reconstructive Surgery",
    "counseling_route": "MCC",
    "quota_type": "All India Basis",
    "seats": 2,
    "seats_prev": 2,
    "seats_inc": 0
  },
  {
    "college_id": "ss_b_j_government_medical_college_pune_maharashtra",
    "college_name": "B. J. Government Medical College, Pune",
    "college_type": "Government",
    "state": "Maharashtra",
    "course": "M.Ch - Paediatric Surgery",
    "counseling_route": "MCC",
    "quota_type": "All India Basis",
    "seats": 2,
    "seats_prev": 2,
    "seats_inc": 0
  },
  {
    "college_id": "ss_b_j_government_medical_college_pune_maharashtra",
    "college_name": "B. J. Government Medical College, Pune",
    "college_type": "Government",
    "state": "Maharashtra",
    "course": "M.Ch - Cardiovascular & Thoracic Surgery",
    "counseling_route": "MCC",
    "quota_type": "All India Basis",
    "seats": 1,
    "seats_prev": 1,
    "seats_inc": 0
  },
  {
    "college_id": "ss_bharati_vidyapeeth_university_medical_college_pune_maharashtra",
    "college_name": "Bharati Vidyapeeth University Medical College, Pune",
    "college_type": "Private",
    "state": "Maharashtra",
    "course": "DM - Critical Care Medicine",
    "counseling_route": "MCC",
    "quota_type": "All India Basis",
    "seats": 10,
    "seats_prev": 6,
    "seats_inc": 4
  },
  {
    "college_id": "ss_bharati_vidyapeeth_university_medical_college_pune_maharashtra",
    "college_name": "Bharati Vidyapeeth University Medical College, Pune",
    "college_type": "Private",
    "state": "Maharashtra",
    "course": "DM - Cardiology",
    "counseling_route": "MCC",
    "quota_type": "All India Basis",
    "seats": 5,
    "seats_prev": 3,
    "seats_inc": 2
  },
  {
    "college_id": "ss_bharati_vidyapeeth_university_medical_college_pune_maharashtra",
    "college_name": "Bharati Vidyapeeth University Medical College, Pune",
    "college_type": "Private",
    "state": "Maharashtra",
    "course": "DM - Neonatology",
    "counseling_route": "MCC",
    "quota_type": "All India Basis",
    "seats": 5,
    "seats_prev": 5,
    "seats_inc": 0
  },
  {
    "college_id": "ss_bharati_vidyapeeth_university_medical_college_pune_maharashtra",
    "college_name": "Bharati Vidyapeeth University Medical College, Pune",
    "college_type": "Private",
    "state": "Maharashtra",
    "course": "DM - Medical Gastroenterology",
    "counseling_route": "MCC",
    "quota_type": "All India Basis",
    "seats": 4,
    "seats_prev": 1,
    "seats_inc": 3
  },
  {
    "college_id": "ss_bharati_vidyapeeth_university_medical_college_pune_maharashtra",
    "college_name": "Bharati Vidyapeeth University Medical College, Pune",
    "college_type": "Private",
    "state": "Maharashtra",
    "course": "DM - Neurology",
    "counseling_route": "MCC",
    "quota_type": "All India Basis",
    "seats": 1,
    "seats_prev": 1,
    "seats_inc": 0
  },
  {
    "college_id": "ss_bharati_vidyapeeth_university_medical_college_pune_maharashtra",
    "college_name": "Bharati Vidyapeeth University Medical College, Pune",
    "college_type": "Private",
    "state": "Maharashtra",
    "course": "DM - Clinical Immunology & Rheumatology",
    "counseling_route": "MCC",
    "quota_type": "All India Basis",
    "seats": 2,
    "seats_prev": 2,
    "seats_inc": 0
  },
  {
    "college_id": "ss_bharati_vidyapeeth_university_medical_college_pune_maharashtra",
    "college_name": "Bharati Vidyapeeth University Medical College, Pune",
    "college_type": "Private",
    "state": "Maharashtra",
    "course": "M.Ch - Urology",
    "counseling_route": "MCC",
    "quota_type": "All India Basis",
    "seats": 3,
    "seats_prev": 3,
    "seats_inc": 0
  },
  {
    "college_id": "ss_bombay_hospital_institute_of_medical_sciences_mumbai_maharashtra",
    "college_name": "Bombay Hospital Institute of Medical Sciences, Mumbai",
    "college_type": "Government",
    "state": "Maharashtra",
    "course": "DM - Cardiology",
    "counseling_route": "MCC",
    "quota_type": "All India Basis",
    "seats": 1,
    "seats_prev": 1,
    "seats_inc": 0
  },
  {
    "college_id": "ss_bombay_hospital_institute_of_medical_sciences_mumbai_maharashtra",
    "college_name": "Bombay Hospital Institute of Medical Sciences, Mumbai",
    "college_type": "Government",
    "state": "Maharashtra",
    "course": "DM - Neurology",
    "counseling_route": "MCC",
    "quota_type": "All India Basis",
    "seats": 2,
    "seats_prev": 2,
    "seats_inc": 0
  },
  {
    "college_id": "ss_bombay_hospital_institute_of_medical_sciences_mumbai_maharashtra",
    "college_name": "Bombay Hospital Institute of Medical Sciences, Mumbai",
    "college_type": "Government",
    "state": "Maharashtra",
    "course": "DM - Nephrology",
    "counseling_route": "MCC",
    "quota_type": "All India Basis",
    "seats": 2,
    "seats_prev": 2,
    "seats_inc": 0
  },
  {
    "college_id": "ss_bombay_hospital_institute_of_medical_sciences_mumbai_maharashtra",
    "college_name": "Bombay Hospital Institute of Medical Sciences, Mumbai",
    "college_type": "Government",
    "state": "Maharashtra",
    "course": "M.Ch - Neuro Surgery",
    "counseling_route": "MCC",
    "quota_type": "All India Basis",
    "seats": 3,
    "seats_prev": 3,
    "seats_inc": 0
  },
  {
    "college_id": "ss_bombay_hospital_institute_of_medical_sciences_mumbai_maharashtra",
    "college_name": "Bombay Hospital Institute of Medical Sciences, Mumbai",
    "college_type": "Government",
    "state": "Maharashtra",
    "course": "M.Ch - Urology",
    "counseling_route": "MCC",
    "quota_type": "All India Basis",
    "seats": 2,
    "seats_prev": 2,
    "seats_inc": 0
  },
  {
    "college_id": "ss_bombay_hospital_institute_of_medical_sciences_mumbai_maharashtra",
    "college_name": "Bombay Hospital Institute of Medical Sciences, Mumbai",
    "college_type": "Government",
    "state": "Maharashtra",
    "course": "M.Ch - Cardiovascular & Thoracic Surgery",
    "counseling_route": "MCC",
    "quota_type": "All India Basis",
    "seats": 1,
    "seats_prev": 1,
    "seats_inc": 0
  },
  {
    "college_id": "ss_dr_ulhas_patil_medical_college_hospital_jalgaon_maharashtra",
    "college_name": "Dr. Ulhas Patil Medical College & Hospital, Jalgaon",
    "college_type": "Private",
    "state": "Maharashtra",
    "course": "DM - Cardiology",
    "counseling_route": "MCC",
    "quota_type": "All India Basis",
    "seats": 3,
    "seats_prev": 3,
    "seats_inc": 0
  },
  {
    "college_id": "ss_dr_ulhas_patil_medical_college_hospital_jalgaon_maharashtra",
    "college_name": "Dr. Ulhas Patil Medical College & Hospital, Jalgaon",
    "college_type": "Private",
    "state": "Maharashtra",
    "course": "DM - Neurology",
    "counseling_route": "MCC",
    "quota_type": "All India Basis",
    "seats": 2,
    "seats_prev": 2,
    "seats_inc": 0
  },
  {
    "college_id": "ss_dr_ulhas_patil_medical_college_hospital_jalgaon_maharashtra",
    "college_name": "Dr. Ulhas Patil Medical College & Hospital, Jalgaon",
    "college_type": "Private",
    "state": "Maharashtra",
    "course": "M.Ch - Neuro Surgery",
    "counseling_route": "MCC",
    "quota_type": "All India Basis",
    "seats": 3,
    "seats_prev": 3,
    "seats_inc": 0
  },
  {
    "college_id": "ss_dr_ulhas_patil_medical_college_hospital_jalgaon_maharashtra",
    "college_name": "Dr. Ulhas Patil Medical College & Hospital, Jalgaon",
    "college_type": "Private",
    "state": "Maharashtra",
    "course": "M.Ch - Urology",
    "counseling_route": "MCC",
    "quota_type": "All India Basis",
    "seats": 2,
    "seats_prev": 2,
    "seats_inc": 0
  },
  {
    "college_id": "ss_government_medical_college_aurangabad_maharashtra",
    "college_name": "Government Medical College, Aurangabad",
    "college_type": "Government",
    "state": "Maharashtra",
    "course": "DM - Medical Oncology",
    "counseling_route": "MCC",
    "quota_type": "All India Basis",
    "seats": 4,
    "seats_prev": 4,
    "seats_inc": 0
  },
  {
    "college_id": "ss_government_medical_college_aurangabad_maharashtra",
    "college_name": "Government Medical College, Aurangabad",
    "college_type": "Government",
    "state": "Maharashtra",
    "course": "M.Ch - Gynaecological Oncology",
    "counseling_route": "MCC",
    "quota_type": "All India Basis",
    "seats": 4,
    "seats_prev": 4,
    "seats_inc": 0
  },
  {
    "college_id": "ss_government_medical_college_aurangabad_maharashtra",
    "college_name": "Government Medical College, Aurangabad",
    "college_type": "Government",
    "state": "Maharashtra",
    "course": "M.Ch - Head & Neck Surgery",
    "counseling_route": "MCC",
    "quota_type": "All India Basis",
    "seats": 2,
    "seats_prev": 2,
    "seats_inc": 0
  },
  {
    "college_id": "ss_government_medical_college_aurangabad_maharashtra",
    "college_name": "Government Medical College, Aurangabad",
    "college_type": "Government",
    "state": "Maharashtra",
    "course": "DM - Neonatology",
    "counseling_route": "MCC",
    "quota_type": "All India Basis",
    "seats": 5,
    "seats_prev": 4,
    "seats_inc": 1
  },
  {
    "college_id": "ss_government_medical_college_aurangabad_maharashtra",
    "college_name": "Government Medical College, Aurangabad",
    "college_type": "Government",
    "state": "Maharashtra",
    "course": "M.Ch - Paediatric Surgery",
    "counseling_route": "MCC",
    "quota_type": "All India Basis",
    "seats": 4,
    "seats_prev": 4,
    "seats_inc": 0
  },
  {
    "college_id": "ss_government_medical_college_aurangabad_maharashtra",
    "college_name": "Government Medical College, Aurangabad",
    "college_type": "Government",
    "state": "Maharashtra",
    "course": "M.Ch - Surgical Oncology",
    "counseling_route": "MCC",
    "quota_type": "All India Basis",
    "seats": 3,
    "seats_prev": 3,
    "seats_inc": 0
  },
  {
    "college_id": "ss_government_medical_college_aurangabad_maharashtra",
    "college_name": "Government Medical College, Aurangabad",
    "college_type": "Government",
    "state": "Maharashtra",
    "course": "DM - Paediatric Oncology",
    "counseling_route": "MCC",
    "quota_type": "All India Basis",
    "seats": 4,
    "seats_prev": 4,
    "seats_inc": 0
  },
  {
    "college_id": "ss_government_medical_college_aurangabad_maharashtra",
    "college_name": "Government Medical College, Aurangabad",
    "college_type": "Government",
    "state": "Maharashtra",
    "course": "DM - Onco Pathology",
    "counseling_route": "MCC",
    "quota_type": "All India Basis",
    "seats": 4,
    "seats_prev": 4,
    "seats_inc": 0
  },
  {
    "college_id": "ss_government_medical_college_nagpur_maharashtra",
    "college_name": "Government Medical College, Nagpur",
    "college_type": "Government",
    "state": "Maharashtra",
    "course": "M.Ch - Neuro Surgery",
    "counseling_route": "MCC",
    "quota_type": "All India Basis",
    "seats": 4,
    "seats_prev": 4,
    "seats_inc": 0
  },
  {
    "college_id": "ss_government_medical_college_nagpur_maharashtra",
    "college_name": "Government Medical College, Nagpur",
    "college_type": "Government",
    "state": "Maharashtra",
    "course": "DM - Interventional Radiology",
    "counseling_route": "MCC",
    "quota_type": "All India Basis",
    "seats": 2,
    "seats_prev": 2,
    "seats_inc": 0
  },
  {
    "college_id": "ss_government_medical_college_nagpur_maharashtra",
    "college_name": "Government Medical College, Nagpur",
    "college_type": "Government",
    "state": "Maharashtra",
    "course": "M.Ch - Paediatric Surgery",
    "counseling_route": "MCC",
    "quota_type": "All India Basis",
    "seats": 2,
    "seats_prev": 2,
    "seats_inc": 0
  },
  {
    "college_id": "ss_government_medical_college_nagpur_maharashtra",
    "college_name": "Government Medical College, Nagpur",
    "college_type": "Government",
    "state": "Maharashtra",
    "course": "M.Ch - Plastic & Reconstructive Surgery",
    "counseling_route": "MCC",
    "quota_type": "All India Basis",
    "seats": 2,
    "seats_prev": 2,
    "seats_inc": 0
  },
  {
    "college_id": "ss_government_medical_college_nagpur_maharashtra",
    "college_name": "Government Medical College, Nagpur",
    "college_type": "Government",
    "state": "Maharashtra",
    "course": "DM - Cardiology",
    "counseling_route": "MCC",
    "quota_type": "All India Basis",
    "seats": 4,
    "seats_prev": 4,
    "seats_inc": 0
  },
  {
    "college_id": "ss_government_medical_college_nagpur_maharashtra",
    "college_name": "Government Medical College, Nagpur",
    "college_type": "Government",
    "state": "Maharashtra",
    "course": "DM - Medical Gastroenterology",
    "counseling_route": "MCC",
    "quota_type": "All India Basis",
    "seats": 2,
    "seats_prev": 2,
    "seats_inc": 0
  },
  {
    "college_id": "ss_government_medical_college_nagpur_maharashtra",
    "college_name": "Government Medical College, Nagpur",
    "college_type": "Government",
    "state": "Maharashtra",
    "course": "M.Ch - Urology",
    "counseling_route": "MCC",
    "quota_type": "All India Basis",
    "seats": 2,
    "seats_prev": 2,
    "seats_inc": 0
  },
  {
    "college_id": "ss_grant_medical_college_mumbai_maharashtra",
    "college_name": "Grant Medical College, Mumbai",
    "college_type": "Government",
    "state": "Maharashtra",
    "course": "DM - Cardiology",
    "counseling_route": "MCC",
    "quota_type": "All India Basis",
    "seats": 5,
    "seats_prev": 5,
    "seats_inc": 0
  },
  {
    "college_id": "ss_grant_medical_college_mumbai_maharashtra",
    "college_name": "Grant Medical College, Mumbai",
    "college_type": "Government",
    "state": "Maharashtra",
    "course": "M.Ch - Paediatric Surgery",
    "counseling_route": "MCC",
    "quota_type": "All India Basis",
    "seats": 5,
    "seats_prev": 5,
    "seats_inc": 0
  },
  {
    "college_id": "ss_grant_medical_college_mumbai_maharashtra",
    "college_name": "Grant Medical College, Mumbai",
    "college_type": "Government",
    "state": "Maharashtra",
    "course": "DM - Interventional Radiology",
    "counseling_route": "MCC",
    "quota_type": "All India Basis",
    "seats": 3,
    "seats_prev": 3,
    "seats_inc": 0
  },
  {
    "college_id": "ss_grant_medical_college_mumbai_maharashtra",
    "college_name": "Grant Medical College, Mumbai",
    "college_type": "Government",
    "state": "Maharashtra",
    "course": "DM - Nephrology",
    "counseling_route": "MCC",
    "quota_type": "All India Basis",
    "seats": 3,
    "seats_prev": 3,
    "seats_inc": 0
  },
  {
    "college_id": "ss_grant_medical_college_mumbai_maharashtra",
    "college_name": "Grant Medical College, Mumbai",
    "college_type": "Government",
    "state": "Maharashtra",
    "course": "DM - Neurology",
    "counseling_route": "MCC",
    "quota_type": "All India Basis",
    "seats": 2,
    "seats_prev": 2,
    "seats_inc": 0
  },
  {
    "college_id": "ss_grant_medical_college_mumbai_maharashtra",
    "college_name": "Grant Medical College, Mumbai",
    "college_type": "Government",
    "state": "Maharashtra",
    "course": "M.Ch - Urology",
    "counseling_route": "MCC",
    "quota_type": "All India Basis",
    "seats": 3,
    "seats_prev": 3,
    "seats_inc": 0
  },
  {
    "college_id": "ss_grant_medical_college_mumbai_maharashtra",
    "college_name": "Grant Medical College, Mumbai",
    "college_type": "Government",
    "state": "Maharashtra",
    "course": "M.Ch - Neuro Surgery",
    "counseling_route": "MCC",
    "quota_type": "All India Basis",
    "seats": 3,
    "seats_prev": 3,
    "seats_inc": 0
  },
  {
    "college_id": "ss_grant_medical_college_mumbai_maharashtra",
    "college_name": "Grant Medical College, Mumbai",
    "college_type": "Government",
    "state": "Maharashtra",
    "course": "M.Ch - Cardiovascular & Thoracic Surgery",
    "counseling_route": "MCC",
    "quota_type": "All India Basis",
    "seats": 3,
    "seats_prev": 3,
    "seats_inc": 0
  },
  {
    "college_id": "ss_jawaharlal_nehru_medical_college_sawangi_meghe_wardha_maharashtra",
    "college_name": "Jawaharlal Nehru Medical College, Sawangi (Meghe), Wardha",
    "college_type": "Private",
    "state": "Maharashtra",
    "course": "M.Ch - Neuro Surgery",
    "counseling_route": "MCC",
    "quota_type": "All India Basis",
    "seats": 1,
    "seats_prev": 1,
    "seats_inc": 0
  },
  {
    "college_id": "ss_jawaharlal_nehru_medical_college_sawangi_meghe_wardha_maharashtra",
    "college_name": "Jawaharlal Nehru Medical College, Sawangi (Meghe), Wardha",
    "college_type": "Private",
    "state": "Maharashtra",
    "course": "DM - Critical Care Medicine",
    "counseling_route": "MCC",
    "quota_type": "All India Basis",
    "seats": 2,
    "seats_prev": 2,
    "seats_inc": 0
  },
  {
    "college_id": "ss_jawaharlal_nehru_medical_college_sawangi_meghe_wardha_maharashtra",
    "college_name": "Jawaharlal Nehru Medical College, Sawangi (Meghe), Wardha",
    "college_type": "Private",
    "state": "Maharashtra",
    "course": "DM - Medical Gastroenterology",
    "counseling_route": "MCC",
    "quota_type": "All India Basis",
    "seats": 4,
    "seats_prev": 2,
    "seats_inc": 2
  },
  {
    "college_id": "ss_jawaharlal_nehru_medical_college_sawangi_meghe_wardha_maharashtra",
    "college_name": "Jawaharlal Nehru Medical College, Sawangi (Meghe), Wardha",
    "college_type": "Private",
    "state": "Maharashtra",
    "course": "DM - Interventional Radiology",
    "counseling_route": "MCC",
    "quota_type": "All India Basis",
    "seats": 4,
    "seats_prev": 2,
    "seats_inc": 2
  },
  {
    "college_id": "ss_jawaharlal_nehru_medical_college_sawangi_meghe_wardha_maharashtra",
    "college_name": "Jawaharlal Nehru Medical College, Sawangi (Meghe), Wardha",
    "college_type": "Private",
    "state": "Maharashtra",
    "course": "DM - Cardiology",
    "counseling_route": "MCC",
    "quota_type": "All India Basis",
    "seats": 4,
    "seats_prev": 2,
    "seats_inc": 2
  },
  {
    "college_id": "ss_jawaharlal_nehru_medical_college_sawangi_meghe_wardha_maharashtra",
    "college_name": "Jawaharlal Nehru Medical College, Sawangi (Meghe), Wardha",
    "college_type": "Private",
    "state": "Maharashtra",
    "course": "DM - Neonatology",
    "counseling_route": "MCC",
    "quota_type": "All India Basis",
    "seats": 1,
    "seats_prev": 1,
    "seats_inc": 0
  },
  {
    "college_id": "ss_jawaharlal_nehru_medical_college_sawangi_meghe_wardha_maharashtra",
    "college_name": "Jawaharlal Nehru Medical College, Sawangi (Meghe), Wardha",
    "college_type": "Private",
    "state": "Maharashtra",
    "course": "DM - Nephrology",
    "counseling_route": "MCC",
    "quota_type": "All India Basis",
    "seats": 3,
    "seats_prev": 3,
    "seats_inc": 0
  },
  {
    "college_id": "ss_jawaharlal_nehru_medical_college_sawangi_meghe_wardha_maharashtra",
    "college_name": "Jawaharlal Nehru Medical College, Sawangi (Meghe), Wardha",
    "college_type": "Private",
    "state": "Maharashtra",
    "course": "DM - Medical Oncology",
    "counseling_route": "MCC",
    "quota_type": "All India Basis",
    "seats": 2,
    "seats_prev": 2,
    "seats_inc": 0
  },
  {
    "college_id": "ss_jawaharlal_nehru_medical_college_sawangi_meghe_wardha_maharashtra",
    "college_name": "Jawaharlal Nehru Medical College, Sawangi (Meghe), Wardha",
    "college_type": "Private",
    "state": "Maharashtra",
    "course": "M.Ch - Urology",
    "counseling_route": "MCC",
    "quota_type": "All India Basis",
    "seats": 1,
    "seats_prev": 1,
    "seats_inc": 0
  },
  {
    "college_id": "ss_jawaharlal_nehru_medical_college_sawangi_meghe_wardha_maharashtra",
    "college_name": "Jawaharlal Nehru Medical College, Sawangi (Meghe), Wardha",
    "college_type": "Private",
    "state": "Maharashtra",
    "course": "DM - Neurology",
    "counseling_route": "MCC",
    "quota_type": "All India Basis",
    "seats": 4,
    "seats_prev": 4,
    "seats_inc": 0
  },
  {
    "college_id": "ss_krishna_institute_of_medical_sciences_karad_maharashtra",
    "college_name": "Krishna Institute of Medical Sciences, Karad",
    "college_type": "Private",
    "state": "Maharashtra",
    "course": "M.Ch - Neuro Surgery",
    "counseling_route": "MCC",
    "quota_type": "All India Basis",
    "seats": 3,
    "seats_prev": 1,
    "seats_inc": 2
  },
  {
    "college_id": "ss_krishna_institute_of_medical_sciences_karad_maharashtra",
    "college_name": "Krishna Institute of Medical Sciences, Karad",
    "college_type": "Private",
    "state": "Maharashtra",
    "course": "M.Ch - Plastic & Reconstructive Surgery",
    "counseling_route": "MCC",
    "quota_type": "All India Basis",
    "seats": 1,
    "seats_prev": 1,
    "seats_inc": 0
  },
  {
    "college_id": "ss_krishna_institute_of_medical_sciences_karad_maharashtra",
    "college_name": "Krishna Institute of Medical Sciences, Karad",
    "college_type": "Private",
    "state": "Maharashtra",
    "course": "M.Ch - Urology",
    "counseling_route": "MCC",
    "quota_type": "All India Basis",
    "seats": 3,
    "seats_prev": 2,
    "seats_inc": 1
  },
  {
    "college_id": "ss_krishna_institute_of_medical_sciences_karad_maharashtra",
    "college_name": "Krishna Institute of Medical Sciences, Karad",
    "college_type": "Private",
    "state": "Maharashtra",
    "course": "DM - Cardiology",
    "counseling_route": "MCC",
    "quota_type": "All India Basis",
    "seats": 2,
    "seats_prev": 2,
    "seats_inc": 0
  },
  {
    "college_id": "ss_krishna_institute_of_medical_sciences_karad_maharashtra",
    "college_name": "Krishna Institute of Medical Sciences, Karad",
    "college_type": "Private",
    "state": "Maharashtra",
    "course": "DM - Critical Care Medicine",
    "counseling_route": "MCC",
    "quota_type": "All India Basis",
    "seats": 4,
    "seats_prev": 4,
    "seats_inc": 0
  },
  {
    "college_id": "ss_krishna_institute_of_medical_sciences_karad_maharashtra",
    "college_name": "Krishna Institute of Medical Sciences, Karad",
    "college_type": "Private",
    "state": "Maharashtra",
    "course": "DM - Neuro Anaesthesia",
    "counseling_route": "MCC",
    "quota_type": "All India Basis",
    "seats": 4,
    "seats_prev": 4,
    "seats_inc": 0
  },
  {
    "college_id": "ss_lokmanya_tilak_municipal_medical_college_sion_mumbai_maharashtra",
    "college_name": "Lokmanya Tilak Municipal Medical College, Sion, Mumbai",
    "college_type": "Government",
    "state": "Maharashtra",
    "course": "DM - Cardiology",
    "counseling_route": "MCC",
    "quota_type": "All India Basis",
    "seats": 4,
    "seats_prev": 4,
    "seats_inc": 0
  },
  {
    "college_id": "ss_lokmanya_tilak_municipal_medical_college_sion_mumbai_maharashtra",
    "college_name": "Lokmanya Tilak Municipal Medical College, Sion, Mumbai",
    "college_type": "Government",
    "state": "Maharashtra",
    "course": "DM - Medical Gastroenterology",
    "counseling_route": "MCC",
    "quota_type": "All India Basis",
    "seats": 4,
    "seats_prev": 4,
    "seats_inc": 0
  },
  {
    "college_id": "ss_lokmanya_tilak_municipal_medical_college_sion_mumbai_maharashtra",
    "college_name": "Lokmanya Tilak Municipal Medical College, Sion, Mumbai",
    "college_type": "Government",
    "state": "Maharashtra",
    "course": "DM - Neonatology",
    "counseling_route": "MCC",
    "quota_type": "All India Basis",
    "seats": 3,
    "seats_prev": 3,
    "seats_inc": 0
  },
  {
    "college_id": "ss_lokmanya_tilak_municipal_medical_college_sion_mumbai_maharashtra",
    "college_name": "Lokmanya Tilak Municipal Medical College, Sion, Mumbai",
    "college_type": "Government",
    "state": "Maharashtra",
    "course": "M.Ch - Urology",
    "counseling_route": "MCC",
    "quota_type": "All India Basis",
    "seats": 4,
    "seats_prev": 4,
    "seats_inc": 0
  },
  {
    "college_id": "ss_lokmanya_tilak_municipal_medical_college_sion_mumbai_maharashtra",
    "college_name": "Lokmanya Tilak Municipal Medical College, Sion, Mumbai",
    "college_type": "Government",
    "state": "Maharashtra",
    "course": "M.Ch - Plastic & Reconstructive Surgery",
    "counseling_route": "MCC",
    "quota_type": "All India Basis",
    "seats": 4,
    "seats_prev": 4,
    "seats_inc": 0
  },
  {
    "college_id": "ss_lokmanya_tilak_municipal_medical_college_sion_mumbai_maharashtra",
    "college_name": "Lokmanya Tilak Municipal Medical College, Sion, Mumbai",
    "college_type": "Government",
    "state": "Maharashtra",
    "course": "M.Ch - Neuro Surgery",
    "counseling_route": "MCC",
    "quota_type": "All India Basis",
    "seats": 4,
    "seats_prev": 4,
    "seats_inc": 0
  },
  {
    "college_id": "ss_lokmanya_tilak_municipal_medical_college_sion_mumbai_maharashtra",
    "college_name": "Lokmanya Tilak Municipal Medical College, Sion, Mumbai",
    "college_type": "Government",
    "state": "Maharashtra",
    "course": "M.Ch - Paediatric Surgery",
    "counseling_route": "MCC",
    "quota_type": "All India Basis",
    "seats": 4,
    "seats_prev": 4,
    "seats_inc": 0
  },
  {
    "college_id": "ss_lokmanya_tilak_municipal_medical_college_sion_mumbai_maharashtra",
    "college_name": "Lokmanya Tilak Municipal Medical College, Sion, Mumbai",
    "college_type": "Government",
    "state": "Maharashtra",
    "course": "M.Ch - Cardiovascular & Thoracic Surgery",
    "counseling_route": "MCC",
    "quota_type": "All India Basis",
    "seats": 3,
    "seats_prev": 3,
    "seats_inc": 0
  },
  {
    "college_id": "ss_mahatma_gandhi_missions_medical_college_aurangabad_maharashtra",
    "college_name": "Mahatma Gandhi Missions Medical College Aurangabad",
    "college_type": "Private",
    "state": "Maharashtra",
    "course": "DM - Cardiology",
    "counseling_route": "MCC",
    "quota_type": "All India Basis",
    "seats": 4,
    "seats_prev": 4,
    "seats_inc": 0
  },
  {
    "college_id": "ss_mahatma_gandhi_missions_medical_college_aurangabad_maharashtra",
    "college_name": "Mahatma Gandhi Missions Medical College Aurangabad",
    "college_type": "Private",
    "state": "Maharashtra",
    "course": "DM - Nephrology",
    "counseling_route": "MCC",
    "quota_type": "All India Basis",
    "seats": 1,
    "seats_prev": 1,
    "seats_inc": 0
  },
  {
    "college_id": "ss_mahatma_gandhi_missions_medical_college_aurangabad_maharashtra",
    "college_name": "Mahatma Gandhi Missions Medical College Aurangabad",
    "college_type": "Private",
    "state": "Maharashtra",
    "course": "M.Ch - Plastic & Reconstructive Surgery",
    "counseling_route": "MCC",
    "quota_type": "All India Basis",
    "seats": 1,
    "seats_prev": 1,
    "seats_inc": 0
  },
  {
    "college_id": "ss_mahatma_gandhi_missions_medical_college_aurangabad_maharashtra",
    "college_name": "Mahatma Gandhi Missions Medical College Aurangabad",
    "college_type": "Private",
    "state": "Maharashtra",
    "course": "M.Ch - Urology",
    "counseling_route": "MCC",
    "quota_type": "All India Basis",
    "seats": 4,
    "seats_prev": 4,
    "seats_inc": 0
  },
  {
    "college_id": "ss_mahatma_gandhi_missions_medical_college_aurangabad_maharashtra",
    "college_name": "Mahatma Gandhi Missions Medical College Aurangabad",
    "college_type": "Private",
    "state": "Maharashtra",
    "course": "M.Ch - Cardiovascular & Thoracic Surgery",
    "counseling_route": "MCC",
    "quota_type": "All India Basis",
    "seats": 1,
    "seats_prev": 1,
    "seats_inc": 0
  },
  {
    "college_id": "ss_mahatma_gandhi_missions_medical_college_navi_mumbai_maharashtra",
    "college_name": "Mahatma Gandhi Missions Medical College, Navi Mumbai",
    "college_type": "Private",
    "state": "Maharashtra",
    "course": "DM - Cardiology",
    "counseling_route": "MCC",
    "quota_type": "All India Basis",
    "seats": 3,
    "seats_prev": 3,
    "seats_inc": 0
  },
  {
    "college_id": "ss_mahatma_gandhi_missions_medical_college_navi_mumbai_maharashtra",
    "college_name": "Mahatma Gandhi Missions Medical College, Navi Mumbai",
    "college_type": "Private",
    "state": "Maharashtra",
    "course": "M.Ch - Urology",
    "counseling_route": "MCC",
    "quota_type": "All India Basis",
    "seats": 3,
    "seats_prev": 3,
    "seats_inc": 0
  },
  {
    "college_id": "ss_mahatma_gandhi_missions_medical_college_navi_mumbai_maharashtra",
    "college_name": "Mahatma Gandhi Missions Medical College, Navi Mumbai",
    "college_type": "Private",
    "state": "Maharashtra",
    "course": "M.Ch - Cardiovascular & Thoracic Surgery",
    "counseling_route": "MCC",
    "quota_type": "All India Basis",
    "seats": 1,
    "seats_prev": 1,
    "seats_inc": 0
  },
  {
    "college_id": "ss_mahatma_gandhi_missions_medical_college_navi_mumbai_maharashtra",
    "college_name": "Mahatma Gandhi Missions Medical College, Navi Mumbai",
    "college_type": "Private",
    "state": "Maharashtra",
    "course": "M.Ch - Neuro Surgery",
    "counseling_route": "MCC",
    "quota_type": "All India Basis",
    "seats": 3,
    "seats_prev": 3,
    "seats_inc": 0
  },
  {
    "college_id": "ss_n_k_p_salve_institute_of_medical_sciences_and_research_centre_and_lata_mangeshkar_hospital_nagpur_maharashtra",
    "college_name": "N. K. P. Salve Institute of Medical Sciences and Research Centre and Lata Mangeshkar Hospital, Nagpur",
    "college_type": "Private",
    "state": "Maharashtra",
    "course": "M.Ch - Plastic & Reconstructive Surgery",
    "counseling_route": "MCC",
    "quota_type": "All India Basis",
    "seats": 1,
    "seats_prev": 1,
    "seats_inc": 0
  },
  {
    "college_id": "ss_n_k_p_salve_institute_of_medical_sciences_and_research_centre_and_lata_mangeshkar_hospital_nagpur_maharashtra",
    "college_name": "N. K. P. Salve Institute of Medical Sciences and Research Centre and Lata Mangeshkar Hospital, Nagpur",
    "college_type": "Private",
    "state": "Maharashtra",
    "course": "M.Ch - Paediatric Surgery",
    "counseling_route": "MCC",
    "quota_type": "All India Basis",
    "seats": 1,
    "seats_prev": 1,
    "seats_inc": 0
  },
  {
    "college_id": "ss_padmashree_dr_dypatil_medical_college_navi_mumbai_maharashtra",
    "college_name": "Padmashree Dr. D.Y.Patil Medical College, Navi Mumbai",
    "college_type": "Private",
    "state": "Maharashtra",
    "course": "M.Ch - Urology",
    "counseling_route": "MCC",
    "quota_type": "All India Basis",
    "seats": 2,
    "seats_prev": 2,
    "seats_inc": 0
  },
  {
    "college_id": "ss_padmashree_dr_dypatil_medical_college_navi_mumbai_maharashtra",
    "college_name": "Padmashree Dr. D.Y.Patil Medical College, Navi Mumbai",
    "college_type": "Private",
    "state": "Maharashtra",
    "course": "M.Ch - Neuro Surgery",
    "counseling_route": "MCC",
    "quota_type": "All India Basis",
    "seats": 2,
    "seats_prev": 2,
    "seats_inc": 0
  },
  {
    "college_id": "ss_padmashree_dr_dypatil_medical_college_navi_mumbai_maharashtra",
    "college_name": "Padmashree Dr. D.Y.Patil Medical College, Navi Mumbai",
    "college_type": "Private",
    "state": "Maharashtra",
    "course": "DM - Nephrology",
    "counseling_route": "MCC",
    "quota_type": "All India Basis",
    "seats": 2,
    "seats_prev": 2,
    "seats_inc": 0
  },
  {
    "college_id": "ss_padmashree_dr_dypatil_medical_college_navi_mumbai_maharashtra",
    "college_name": "Padmashree Dr. D.Y.Patil Medical College, Navi Mumbai",
    "college_type": "Private",
    "state": "Maharashtra",
    "course": "DM - Cardiology",
    "counseling_route": "MCC",
    "quota_type": "All India Basis",
    "seats": 4,
    "seats_prev": 4,
    "seats_inc": 0
  },
  {
    "college_id": "ss_padmashree_dr_dypatil_medical_college_navi_mumbai_maharashtra",
    "college_name": "Padmashree Dr. D.Y.Patil Medical College, Navi Mumbai",
    "college_type": "Private",
    "state": "Maharashtra",
    "course": "M.Ch - Cardiovascular & Thoracic Surgery",
    "counseling_route": "MCC",
    "quota_type": "All India Basis",
    "seats": 3,
    "seats_prev": 3,
    "seats_inc": 0
  },
  {
    "college_id": "ss_padmashree_dr_dypatil_medical_college_navi_mumbai_maharashtra",
    "college_name": "Padmashree Dr. D.Y.Patil Medical College, Navi Mumbai",
    "college_type": "Private",
    "state": "Maharashtra",
    "course": "DM - Neurology",
    "counseling_route": "MCC",
    "quota_type": "All India Basis",
    "seats": 2,
    "seats_prev": 2,
    "seats_inc": 0
  },
  {
    "college_id": "ss_padmashree_dr_dypatil_medical_college_navi_mumbai_maharashtra",
    "college_name": "Padmashree Dr. D.Y.Patil Medical College, Navi Mumbai",
    "college_type": "Private",
    "state": "Maharashtra",
    "course": "M.Ch - Plastic & Reconstructive Surgery",
    "counseling_route": "MCC",
    "quota_type": "All India Basis",
    "seats": 2,
    "seats_prev": 2,
    "seats_inc": 0
  },
  {
    "college_id": "ss_padmashree_dr_dypatil_medical_college_navi_mumbai_maharashtra",
    "college_name": "Padmashree Dr. D.Y.Patil Medical College, Navi Mumbai",
    "college_type": "Private",
    "state": "Maharashtra",
    "course": "DM - Interventional Radiology",
    "counseling_route": "MCC",
    "quota_type": "All India Basis",
    "seats": 2,
    "seats_prev": 2,
    "seats_inc": 0
  },
  {
    "college_id": "ss_padmashree_dr_dypatil_medical_college_navi_mumbai_maharashtra",
    "college_name": "Padmashree Dr. D.Y.Patil Medical College, Navi Mumbai",
    "college_type": "Private",
    "state": "Maharashtra",
    "course": "M.Ch - Paediatric Surgery",
    "counseling_route": "MCC",
    "quota_type": "All India Basis",
    "seats": 1,
    "seats_prev": 1,
    "seats_inc": 0
  },
  {
    "college_id": "ss_padmashree_dr_dypatil_medical_college_navi_mumbai_maharashtra",
    "college_name": "Padmashree Dr. D.Y.Patil Medical College, Navi Mumbai",
    "college_type": "Private",
    "state": "Maharashtra",
    "course": "DM - Critical Care Medicine",
    "counseling_route": "MCC",
    "quota_type": "All India Basis",
    "seats": 2,
    "seats_prev": 2,
    "seats_inc": 0
  },
  {
    "college_id": "ss_padmashree_dr_dypatil_medical_college_navi_mumbai_maharashtra",
    "college_name": "Padmashree Dr. D.Y.Patil Medical College, Navi Mumbai",
    "college_type": "Private",
    "state": "Maharashtra",
    "course": "DM - Medical Gastroenterology",
    "counseling_route": "MCC",
    "quota_type": "All India Basis",
    "seats": 2,
    "seats_prev": 2,
    "seats_inc": 0
  },
  {
    "college_id": "ss_rajashree_chatrapati_shahu_maharaj_government_medical_college_kolhapur_maharashtra",
    "college_name": "Rajashree Chatrapati Shahu Maharaj Government Medical College, Kolhapur",
    "college_type": "Government",
    "state": "Maharashtra",
    "course": "DM - Cardiology",
    "counseling_route": "MCC",
    "quota_type": "All India Basis",
    "seats": 3,
    "seats_prev": 3,
    "seats_inc": 0
  },
  {
    "college_id": "ss_rajashree_chatrapati_shahu_maharaj_government_medical_college_kolhapur_maharashtra",
    "college_name": "Rajashree Chatrapati Shahu Maharaj Government Medical College, Kolhapur",
    "college_type": "Government",
    "state": "Maharashtra",
    "course": "M.Ch - Cardiovascular & Thoracic Surgery",
    "counseling_route": "MCC",
    "quota_type": "All India Basis",
    "seats": 4,
    "seats_prev": 4,
    "seats_inc": 0
  },
  {
    "college_id": "ss_tata_memorial_centre_mumbai_maharashtra",
    "college_name": "Tata Memorial centre, Mumbai",
    "college_type": "Government",
    "state": "Maharashtra",
    "course": "DM - Medical Gastroenterology",
    "counseling_route": "MCC",
    "quota_type": "All India Basis",
    "seats": 4,
    "seats_prev": 4,
    "seats_inc": 0
  },
  {
    "college_id": "ss_tata_memorial_centre_mumbai_maharashtra",
    "college_name": "Tata Memorial centre, Mumbai",
    "college_type": "Government",
    "state": "Maharashtra",
    "course": "M.Ch - Gynaecological Oncology",
    "counseling_route": "MCC",
    "quota_type": "All India Basis",
    "seats": 4,
    "seats_prev": 4,
    "seats_inc": 0
  },
  {
    "college_id": "ss_tata_memorial_centre_mumbai_maharashtra",
    "college_name": "Tata Memorial centre, Mumbai",
    "college_type": "Government",
    "state": "Maharashtra",
    "course": "M.Ch - Surgical Oncology",
    "counseling_route": "MCC",
    "quota_type": "All India Basis",
    "seats": 24,
    "seats_prev": 24,
    "seats_inc": 0
  },
  {
    "college_id": "ss_tata_memorial_centre_mumbai_maharashtra",
    "college_name": "Tata Memorial centre, Mumbai",
    "college_type": "Government",
    "state": "Maharashtra",
    "course": "M.Ch - Plastic & Reconstructive Surgery",
    "counseling_route": "MCC",
    "quota_type": "All India Basis",
    "seats": 6,
    "seats_prev": 6,
    "seats_inc": 0
  },
  {
    "college_id": "ss_tata_memorial_centre_mumbai_maharashtra",
    "college_name": "Tata Memorial centre, Mumbai",
    "college_type": "Government",
    "state": "Maharashtra",
    "course": "M.Ch - Head & Neck Surgery",
    "counseling_route": "MCC",
    "quota_type": "All India Basis",
    "seats": 6,
    "seats_prev": 6,
    "seats_inc": 0
  },
  {
    "college_id": "ss_tata_memorial_centre_mumbai_maharashtra",
    "college_name": "Tata Memorial centre, Mumbai",
    "college_type": "Government",
    "state": "Maharashtra",
    "course": "DM - Medical Oncology",
    "counseling_route": "MCC",
    "quota_type": "All India Basis",
    "seats": 24,
    "seats_prev": 24,
    "seats_inc": 0
  },
  {
    "college_id": "ss_tata_memorial_centre_mumbai_maharashtra",
    "college_name": "Tata Memorial centre, Mumbai",
    "college_type": "Government",
    "state": "Maharashtra",
    "course": "DM - Paediatric Oncology",
    "counseling_route": "MCC",
    "quota_type": "All India Basis",
    "seats": 6,
    "seats_prev": 6,
    "seats_inc": 0
  },
  {
    "college_id": "ss_tata_memorial_centre_mumbai_maharashtra",
    "college_name": "Tata Memorial centre, Mumbai",
    "college_type": "Government",
    "state": "Maharashtra",
    "course": "DM - Interventional Radiology",
    "counseling_route": "MCC",
    "quota_type": "All India Basis",
    "seats": 4,
    "seats_prev": 4,
    "seats_inc": 0
  },
  {
    "college_id": "ss_tata_memorial_centre_mumbai_maharashtra",
    "college_name": "Tata Memorial centre, Mumbai",
    "college_type": "Government",
    "state": "Maharashtra",
    "course": "DM - Onco Pathology",
    "counseling_route": "MCC",
    "quota_type": "All India Basis",
    "seats": 6,
    "seats_prev": 6,
    "seats_inc": 0
  },
  {
    "college_id": "ss_tata_memorial_centre_mumbai_maharashtra",
    "college_name": "Tata Memorial centre, Mumbai",
    "college_type": "Government",
    "state": "Maharashtra",
    "course": "DM - Critical Care Medicine",
    "counseling_route": "MCC",
    "quota_type": "All India Basis",
    "seats": 6,
    "seats_prev": 6,
    "seats_inc": 0
  },
  {
    "college_id": "ss_topiwala_national_medical_college_mumbai_maharashtra",
    "college_name": "Topiwala National Medical College, Mumbai",
    "college_type": "Government",
    "state": "Maharashtra",
    "course": "DM - Cardiology",
    "counseling_route": "MCC",
    "quota_type": "All India Basis",
    "seats": 3,
    "seats_prev": 3,
    "seats_inc": 0
  },
  {
    "college_id": "ss_topiwala_national_medical_college_mumbai_maharashtra",
    "college_name": "Topiwala National Medical College, Mumbai",
    "college_type": "Government",
    "state": "Maharashtra",
    "course": "DM - Medical Gastroenterology",
    "counseling_route": "MCC",
    "quota_type": "All India Basis",
    "seats": 3,
    "seats_prev": 3,
    "seats_inc": 0
  },
  {
    "college_id": "ss_topiwala_national_medical_college_mumbai_maharashtra",
    "college_name": "Topiwala National Medical College, Mumbai",
    "college_type": "Government",
    "state": "Maharashtra",
    "course": "DM - Neurology",
    "counseling_route": "MCC",
    "quota_type": "All India Basis",
    "seats": 3,
    "seats_prev": 1,
    "seats_inc": 2
  },
  {
    "college_id": "ss_topiwala_national_medical_college_mumbai_maharashtra",
    "college_name": "Topiwala National Medical College, Mumbai",
    "college_type": "Government",
    "state": "Maharashtra",
    "course": "M.Ch - Urology",
    "counseling_route": "MCC",
    "quota_type": "All India Basis",
    "seats": 3,
    "seats_prev": 3,
    "seats_inc": 0
  },
  {
    "college_id": "ss_topiwala_national_medical_college_mumbai_maharashtra",
    "college_name": "Topiwala National Medical College, Mumbai",
    "college_type": "Government",
    "state": "Maharashtra",
    "course": "M.Ch - Plastic & Reconstructive Surgery",
    "counseling_route": "MCC",
    "quota_type": "All India Basis",
    "seats": 4,
    "seats_prev": 4,
    "seats_inc": 0
  },
  {
    "college_id": "ss_topiwala_national_medical_college_mumbai_maharashtra",
    "college_name": "Topiwala National Medical College, Mumbai",
    "college_type": "Government",
    "state": "Maharashtra",
    "course": "M.Ch - Paediatric Surgery",
    "counseling_route": "MCC",
    "quota_type": "All India Basis",
    "seats": 4,
    "seats_prev": 2,
    "seats_inc": 2
  },
  {
    "college_id": "ss_topiwala_national_medical_college_mumbai_maharashtra",
    "college_name": "Topiwala National Medical College, Mumbai",
    "college_type": "Government",
    "state": "Maharashtra",
    "course": "M.Ch - Cardiovascular & Thoracic Surgery",
    "counseling_route": "MCC",
    "quota_type": "All India Basis",
    "seats": 3,
    "seats_prev": 3,
    "seats_inc": 0
  },
  {
    "college_id": "ss_topiwala_national_medical_college_mumbai_maharashtra",
    "college_name": "Topiwala National Medical College, Mumbai",
    "college_type": "Government",
    "state": "Maharashtra",
    "course": "DM - Nephrology",
    "counseling_route": "MCC",
    "quota_type": "All India Basis",
    "seats": 3,
    "seats_prev": 3,
    "seats_inc": 0
  },
  {
    "college_id": "ss_topiwala_national_medical_college_mumbai_maharashtra",
    "college_name": "Topiwala National Medical College, Mumbai",
    "college_type": "Government",
    "state": "Maharashtra",
    "course": "M.Ch - Neuro Surgery",
    "counseling_route": "MCC",
    "quota_type": "All India Basis",
    "seats": 4,
    "seats_prev": 4,
    "seats_inc": 0
  },
  {
    "college_id": "ss_topiwala_national_medical_college_mumbai_maharashtra",
    "college_name": "Topiwala National Medical College, Mumbai",
    "college_type": "Government",
    "state": "Maharashtra",
    "course": "DM - Endocrinology",
    "counseling_route": "MCC",
    "quota_type": "All India Basis",
    "seats": 2,
    "seats_prev": 2,
    "seats_inc": 0
  },
  {
    "college_id": "ss_dr_d_y_patil_medical_college_hospital_and_research_centre_pimpri_pune_maharashtra",
    "college_name": "Dr. D Y Patil Medical College, Hospital and Research Centre, Pimpri, Pune",
    "college_type": "Private",
    "state": "Maharashtra",
    "course": "M.Ch - Cardiovascular & Thoracic Surgery",
    "counseling_route": "MCC",
    "quota_type": "All India Basis",
    "seats": 3,
    "seats_prev": 3,
    "seats_inc": 0
  },
  {
    "college_id": "ss_dr_d_y_patil_medical_college_hospital_and_research_centre_pimpri_pune_maharashtra",
    "college_name": "Dr. D Y Patil Medical College, Hospital and Research Centre, Pimpri, Pune",
    "college_type": "Private",
    "state": "Maharashtra",
    "course": "DM - Cardiology",
    "counseling_route": "MCC",
    "quota_type": "All India Basis",
    "seats": 3,
    "seats_prev": 3,
    "seats_inc": 0
  },
  {
    "college_id": "ss_dr_d_y_patil_medical_college_hospital_and_research_centre_pimpri_pune_maharashtra",
    "college_name": "Dr. D Y Patil Medical College, Hospital and Research Centre, Pimpri, Pune",
    "college_type": "Private",
    "state": "Maharashtra",
    "course": "DM - Medical Gastroenterology",
    "counseling_route": "MCC",
    "quota_type": "All India Basis",
    "seats": 2,
    "seats_prev": 2,
    "seats_inc": 0
  },
  {
    "college_id": "ss_dr_dypatil_medical_college_pune_maharashtra",
    "college_name": "Dr. D.Y.Patil Medical College, Pune",
    "college_type": "Private",
    "state": "Maharashtra",
    "course": "DM - Critical Care Medicine",
    "counseling_route": "MCC",
    "quota_type": "All India Basis",
    "seats": 2,
    "seats_prev": 2,
    "seats_inc": 0
  },
  {
    "college_id": "ss_dr_d_y_patil_medical_college_hospital_and_research_centre_pimpri_pune_maharashtra",
    "college_name": "Dr. D Y Patil Medical College, Hospital and Research Centre, Pimpri, Pune",
    "college_type": "Private",
    "state": "Maharashtra",
    "course": "DM - Interventional Radiology",
    "counseling_route": "MCC",
    "quota_type": "All India Basis",
    "seats": 2,
    "seats_prev": 2,
    "seats_inc": 0
  },
  {
    "college_id": "ss_dr_d_y_patil_medical_college_hospital_and_research_centre_pimpri_pune_maharashtra",
    "college_name": "Dr. D Y Patil Medical College, Hospital and Research Centre, Pimpri, Pune",
    "college_type": "Private",
    "state": "Maharashtra",
    "course": "DM - Nephrology",
    "counseling_route": "MCC",
    "quota_type": "All India Basis",
    "seats": 3,
    "seats_prev": 3,
    "seats_inc": 0
  },
  {
    "college_id": "ss_dr_d_y_patil_medical_college_hospital_and_research_centre_pimpri_pune_maharashtra",
    "college_name": "Dr. D Y Patil Medical College, Hospital and Research Centre, Pimpri, Pune",
    "college_type": "Private",
    "state": "Maharashtra",
    "course": "DM - Neurology",
    "counseling_route": "MCC",
    "quota_type": "All India Basis",
    "seats": 2,
    "seats_prev": 2,
    "seats_inc": 0
  },
  {
    "college_id": "ss_dr_d_y_patil_medical_college_hospital_and_research_centre_pimpri_pune_maharashtra",
    "college_name": "Dr. D Y Patil Medical College, Hospital and Research Centre, Pimpri, Pune",
    "college_type": "Private",
    "state": "Maharashtra",
    "course": "M.Ch - Neuro Surgery",
    "counseling_route": "MCC",
    "quota_type": "All India Basis",
    "seats": 3,
    "seats_prev": 3,
    "seats_inc": 0
  },
  {
    "college_id": "ss_dr_d_y_patil_medical_college_hospital_and_research_centre_pimpri_pune_maharashtra",
    "college_name": "Dr. D Y Patil Medical College, Hospital and Research Centre, Pimpri, Pune",
    "college_type": "Private",
    "state": "Maharashtra",
    "course": "M.Ch - Plastic & Reconstructive Surgery",
    "counseling_route": "MCC",
    "quota_type": "All India Basis",
    "seats": 2,
    "seats_prev": 2,
    "seats_inc": 0
  },
  {
    "college_id": "ss_dr_d_y_patil_medical_college_hospital_and_research_centre_pimpri_pune_maharashtra",
    "college_name": "Dr. D Y Patil Medical College, Hospital and Research Centre, Pimpri, Pune",
    "college_type": "Private",
    "state": "Maharashtra",
    "course": "M.Ch - Paediatric Surgery",
    "counseling_route": "MCC",
    "quota_type": "All India Basis",
    "seats": 2,
    "seats_prev": 2,
    "seats_inc": 0
  },
  {
    "college_id": "ss_dr_d_y_patil_medical_college_hospital_and_research_centre_pimpri_pune_maharashtra",
    "college_name": "Dr. D Y Patil Medical College, Hospital and Research Centre, Pimpri, Pune",
    "college_type": "Private",
    "state": "Maharashtra",
    "course": "M.Ch - Surgical Oncology",
    "counseling_route": "MCC",
    "quota_type": "All India Basis",
    "seats": 2,
    "seats_prev": 2,
    "seats_inc": 0
  },
  {
    "college_id": "ss_dr_d_y_patil_medical_college_hospital_and_research_centre_pimpri_pune_maharashtra",
    "college_name": "Dr. D Y Patil Medical College, Hospital and Research Centre, Pimpri, Pune",
    "college_type": "Private",
    "state": "Maharashtra",
    "course": "M.Ch - Urology",
    "counseling_route": "MCC",
    "quota_type": "All India Basis",
    "seats": 4,
    "seats_prev": 4,
    "seats_inc": 0
  },
  {
    "college_id": "ss_grant_medical_college_mumbai_maharashtra",
    "college_name": "Grant Medical College, Mumbai",
    "college_type": "Government",
    "state": "Maharashtra",
    "course": "M.Ch - Plastic & Reconstructive Surgery",
    "counseling_route": "MCC",
    "quota_type": "All India Basis",
    "seats": 9,
    "seats_prev": 9,
    "seats_inc": 0
  },
  {
    "college_id": "ss_bharati_vidyapeeth_university_medical_college_pune_maharashtra",
    "college_name": "Bharati Vidyapeeth University Medical College, Pune",
    "college_type": "Private",
    "state": "Maharashtra",
    "course": "DM - Interventional Radiology",
    "counseling_route": "MCC",
    "quota_type": "All India Basis",
    "seats": 1,
    "seats_prev": 1,
    "seats_inc": 0
  },
  {
    "college_id": "ss_lokmanya_tilak_municipal_medical_college_sion_mumbai_maharashtra",
    "college_name": "Lokmanya Tilak Municipal Medical College, Sion, Mumbai",
    "college_type": "Government",
    "state": "Maharashtra",
    "course": "DM - Interventional Radiology",
    "counseling_route": "MCC",
    "quota_type": "All India Basis",
    "seats": 2,
    "seats_prev": 0,
    "seats_inc": 2
  },
  {
    "college_id": "ss_dr_d_y_patil_medical_college_hospital_and_research_centre_pimpri_pune_maharashtra",
    "college_name": "Dr. D Y Patil Medical College, Hospital and Research Centre, Pimpri, Pune",
    "college_type": "Private",
    "state": "Maharashtra",
    "course": "M.Ch - Surgical Gastroenterology",
    "counseling_route": "MCC",
    "quota_type": "All India Basis",
    "seats": 2,
    "seats_prev": 0,
    "seats_inc": 2
  },
  {
    "college_id": "ss_seth_gs_medical_college_and_kem_hospital_mumbai_maharashtra",
    "college_name": "Seth GS Medical College, and KEM Hospital, Mumbai",
    "college_type": "Government",
    "state": "Maharashtra",
    "course": "DM - Interventional Radiology",
    "counseling_route": "MCC",
    "quota_type": "All India Basis",
    "seats": 2,
    "seats_prev": 0,
    "seats_inc": 2
  },
  {
    "college_id": "ss_smbt_institute_of_medical_sciences_research_centre_nandihills_nashik_maharashtra",
    "college_name": "SMBT Institute of Medical Sciences & Research Centre, Nandihills, Nashik",
    "college_type": "Private",
    "state": "Maharashtra",
    "course": "DM - Cardiology",
    "counseling_route": "MCC",
    "quota_type": "All India Basis",
    "seats": 3,
    "seats_prev": 0,
    "seats_inc": 3
  },
  {
    "college_id": "ss_topiwala_national_medical_college_mumbai_maharashtra",
    "college_name": "Topiwala National Medical College, Mumbai",
    "college_type": "Government",
    "state": "Maharashtra",
    "course": "DM - Interventional Radiology",
    "counseling_route": "MCC",
    "quota_type": "All India Basis",
    "seats": 2,
    "seats_prev": 0,
    "seats_inc": 2
  },
  {
    "college_id": "ss_dr_d_y_patil_medical_college_hospital_and_research_centre_pimpri_pune_maharashtra",
    "college_name": "Dr. D Y Patil Medical College, Hospital and Research Centre, Pimpri, Pune",
    "college_type": "Private",
    "state": "Maharashtra",
    "course": "DM - Endocrinology",
    "counseling_route": "MCC",
    "quota_type": "All India Basis",
    "seats": 2,
    "seats_prev": 0,
    "seats_inc": 2
  },
  {
    "college_id": "ss_dr_ulhas_patil_medical_college_hospital_jalgaon_maharashtra",
    "college_name": "Dr. Ulhas Patil Medical College & Hospital, Jalgaon",
    "college_type": "Private",
    "state": "Maharashtra",
    "course": "DM - Nephrology",
    "counseling_route": "MCC",
    "quota_type": "All India Basis",
    "seats": 1,
    "seats_prev": 0,
    "seats_inc": 1
  },
  {
    "college_id": "ss_mahatma_gandhi_missions_medical_college_aurangabad_maharashtra",
    "college_name": "Mahatma Gandhi Missions Medical College Aurangabad",
    "college_type": "Private",
    "state": "Maharashtra",
    "course": "M.Ch - Hepato Pancreato Biliary Surgery",
    "counseling_route": "MCC",
    "quota_type": "All India Basis",
    "seats": 2,
    "seats_prev": 0,
    "seats_inc": 2
  }
]