[
  {
    "college_id": "ug_pb001p4",
    "college_name": "Adesh Institute of Medical Sciences & Research, Bhatinda",
    "college_type": "Private",
    "state": "Punjab",
    "course": "MBBS",
    "counseling_route": "STATE",
    "quota_type": "Competent Authority Quota",
    "seats": 75,
    "seats_prev": 75,
    "seats_inc": 0,
    "pg_seats": 84,
    "ss_seats": 0
  },
  {
    "college_id": "ug_pb001p4",
    "college_name": "Adesh Institute of Medical Sciences & Research, Bhatinda",
    "college_type": "Private",
    "state": "Punjab",
    "course": "MBBS",
    "counseling_route": "STATE",
    "quota_type": "Management Quota",
    "seats": 52,
    "seats_prev": 52,
    "seats_inc": 0,
    "pg_seats": 84,
    "ss_seats": 0
  },
  {
    "college_id": "ug_pb001p4",
    "college_name": "Adesh Institute of Medical Sciences & Research, Bhatinda",
    "college_type": "Private",
    "state": "Punjab",
    "course": "MBBS",
    "counseling_route": "STATE",
    "quota_type": "NRI / Minority Quota",
    "seats": 23,
    "seats_prev": 23,
    "seats_inc": 0,
    "pg_seats": 84,
    "ss_seats": 0
  },
  {
    "college_id": "ug_pb002p4",
    "college_name": "Christian Medical College, Ludhiana",
    "college_type": "Private",
    "state": "Punjab",
    "course": "MBBS",
    "counseling_route": "STATE",
    "quota_type": "Competent Authority Quota",
    "seats": 50,
    "seats_prev": 50,
    "seats_inc": 0,
    "pg_seats": 76,
    "ss_seats": 13
  },
  {
    "college_id": "ug_pb002p4",
    "college_name": "Christian Medical College, Ludhiana",
    "college_type": "Private",
    "state": "Punjab",
    "course": "MBBS",
    "counseling_route": "STATE",
    "quota_type": "Management Quota",
    "seats": 35,
    "seats_prev": 35,
    "seats_inc": 0,
    "pg_seats": 76,
    "ss_seats": 13
  },
  {
    "college_id": "ug_pb002p4",
    "college_name": "Christian Medical College, Ludhiana",
    "college_type": "Private",
    "state": "Punjab",
    "course": "MBBS",
    "counseling_route": "STATE",
    "quota_type": "NRI / Minority Quota",
    "seats": 15,
    "seats_prev": 15,
    "seats_inc": 0,
    "pg_seats": 76,
    "ss_seats": 13
  },
  {
    "college_id": "ug_pb003p3",
    "college_name": "Dayanand Medical College & Hospital, Ludhiana",
    "college_type": "Private",
    "state": "Punjab",
    "course": "MBBS",
    "counseling_route": "STATE",
    "quota_type": "Competent Authority Quota",
    "seats": 75,
    "seats_prev": 75,
    "seats_inc": 0,
    "pg_seats": 107,
    "ss_seats": 35
  },
  {
    "college_id": "ug_pb003p3",
    "college_name": "Dayanand Medical College & Hospital, Ludhiana",
    "college_type": "Private",
    "state": "Punjab",
    "course": "MBBS",
    "counseling_route": "STATE",
    "quota_type": "Management Quota",
    "seats": 52,
    "seats_prev": 52,
    "seats_inc": 0,
    "pg_seats": 107,
    "ss_seats": 35
  },
  {
    "college_id": "ug_pb003p3",
    "college_name": "Dayanand Medical College & Hospital, Ludhiana",
    "college_type": "Private",
    "state": "Punjab",
    "course": "MBBS",
    "counseling_route": "STATE",
    "quota_type": "NRI / Minority Quota",
    "seats": 23,
    "seats_prev": 23,
    "seats_inc": 0,
    "pg_seats": 107,
    "ss_seats": 35
  },
  {
    "college_id": "ug_pb004g1",
    "college_name": "Dr B R Ambedkar State Institute of Medical Sciences, SAS Nagar, Mohali",
    "college_type": "Government",
    "state": "Punjab",
    "course": "MBBS",
    "counseling_route": "MCC",
    "quota_type": "All India Quota",
    "seats": 15,
    "seats_prev": 15,
    "seats_inc": 0,
    "pg_seats": 8,
    "ss_seats": 0
  },
  {
    "college_id": "ug_pb004g1",
    "college_name": "Dr B R Ambedkar State Institute of Medical Sciences, SAS Nagar, Mohali",
    "college_type": "Government",
    "state": "Punjab",
    "course": "MBBS",
    "counseling_route": "STATE",
    "quota_type": "Competent Authority Quota",
    "seats": 85,
    "seats_prev": 85,
    "seats_inc": 0,
    "pg_seats": 8,
    "ss_seats": 0
  },
  {
    "college_id": "ug_pb005g1",
    "college_name": "ESIC Medical College Ludhiana",
    "college_type": "Government",
    "state": "Punjab",
    "course": "MBBS",
    "counseling_route": "MCC",
    "quota_type": "All India Quota",
    "seats": 7,
    "seats_prev": 7,
    "seats_inc": 0,
    "pg_seats": 0,
    "ss_seats": 0
  },
  {
    "college_id": "ug_pb005g1",
    "college_name": "ESIC Medical College Ludhiana",
    "college_type": "Government",
    "state": "Punjab",
    "course": "MBBS",
    "counseling_route": "STATE",
    "quota_type": "Competent Authority Quota",
    "seats": 43,
    "seats_prev": 43,
    "seats_inc": 0,
    "pg_seats": 0,
    "ss_seats": 0
  },
  {
    "college_id": "ug_pb006p3",
    "college_name": "Gian Sagar Medical College & Hospital, Patiala",
    "college_type": "Private",
    "state": "Punjab",
    "course": "MBBS",
    "counseling_route": "STATE",
    "quota_type": "Competent Authority Quota",
    "seats": 75,
    "seats_prev": 75,
    "seats_inc": 0,
    "pg_seats": 28,
    "ss_seats": 0
  },
  {
    "college_id": "ug_pb006p3",
    "college_name": "Gian Sagar Medical College & Hospital, Patiala",
    "college_type": "Private",
    "state": "Punjab",
    "course": "MBBS",
    "counseling_route": "STATE",
    "quota_type": "Management Quota",
    "seats": 52,
    "seats_prev": 52,
    "seats_inc": 0,
    "pg_seats": 28,
    "ss_seats": 0
  },
  {
    "college_id": "ug_pb006p3",
    "college_name": "Gian Sagar Medical College & Hospital, Patiala",
    "college_type": "Private",
    "state": "Punjab",
    "course": "MBBS",
    "counseling_route": "STATE",
    "quota_type": "NRI / Minority Quota",
    "seats": 23,
    "seats_prev": 23,
    "seats_inc": 0,
    "pg_seats": 28,
    "ss_seats": 0
  },
  {
    "college_id": "ug_pb007g1",
    "college_name": "Government Medical College, Amritsar",
    "college_type": "Government",
    "state": "Punjab",
    "course": "MBBS",
    "counseling_route": "MCC",
    "quota_type": "All India Quota",
    "seats": 37,
    "seats_prev": 37,
    "seats_inc": 0,
    "pg_seats": 162,
    "ss_seats": 5
  },
  {
    "college_id": "ug_pb007g1",
    "college_name": "Government Medical College, Amritsar",
    "college_type": "Government",
    "state": "Punjab",
    "course": "MBBS",
    "counseling_route": "STATE",
    "quota_type": "Competent Authority Quota",
    "seats": 213,
    "seats_prev": 213,
    "seats_inc": 0,
    "pg_seats": 162,
    "ss_seats": 5
  },
  {
    "college_id": "ug_pb008g1",
    "college_name": "Government Medical College, Patiala",
    "college_type": "Government",
    "state": "Punjab",
    "course": "MBBS",
    "counseling_route": "MCC",
    "quota_type": "All India Quota",
    "seats": 37,
    "seats_prev": 37,
    "seats_inc": 0,
    "pg_seats": 160,
    "ss_seats": 0
  },
  {
    "college_id": "ug_pb008g1",
    "college_name": "Government Medical College, Patiala",
    "college_type": "Government",
    "state": "Punjab",
    "course": "MBBS",
    "counseling_route": "STATE",
    "quota_type": "Competent Authority Quota",
    "seats": 213,
    "seats_prev": 213,
    "seats_inc": 0,
    "pg_seats": 160,
    "ss_seats": 0
  },
  {
    "college_id": "ug_pb009g1",
    "college_name": "Guru Govind Singh Medical College, Faridkot",
    "college_type": "Government",
    "state": "Punjab",
    "course": "MBBS",
    "counseling_route": "MCC",
    "quota_type": "All India Quota",
    "seats": 37,
    "seats_prev": 37,
    "seats_inc": 0,
    "pg_seats": 127,
    "ss_seats": 4
  },
  {
    "college_id": "ug_pb009g1",
    "college_name": "Guru Govind Singh Medical College, Faridkot",
    "college_type": "Government",
    "state": "Punjab",
    "course": "MBBS",
    "counseling_route": "STATE",
    "quota_type": "Competent Authority Quota",
    "seats": 213,
    "seats_prev": 213,
    "seats_inc": 0,
    "pg_seats": 127,
    "ss_seats": 4
  },
  {
    "college_id": "ug_pb010p4",
    "college_name": "Punjab Institute of Medical Sciences, Jalandhar",
    "college_type": "Private",
    "state": "Punjab",
    "course": "MBBS",
    "counseling_route": "STATE",
    "quota_type": "Competent Authority Quota",
    "seats": 75,
    "seats_prev": 75,
    "seats_inc": 0,
    "pg_seats": 0,
    "ss_seats": 0
  },
  {
    "college_id": "ug_pb010p4",
    "college_name": "Punjab Institute of Medical Sciences, Jalandhar",
    "college_type": "Private",
    "state": "Punjab",
    "course": "MBBS",
    "counseling_route": "STATE",
    "quota_type": "Management Quota",
    "seats": 52,
    "seats_prev": 52,
    "seats_inc": 0,
    "pg_seats": 0,
    "ss_seats": 0
  },
  {
    "college_id": "ug_pb010p4",
    "college_name": "Punjab Institute of Medical Sciences, Jalandhar",
    "college_type": "Private",
    "state": "Punjab",
    "course": "MBBS",
    "counseling_route": "STATE",
    "quota_type": "NRI / Minority Quota",
    "seats": 23,
    "seats_prev": 23,
    "seats_inc": 0,
    "pg_seats": 0,
    "ss_seats": 0
  },
  {
    "college_id": "ug_pb011p3",
    "college_name": "RIMT Medical College and Hospital",
    "college_type": "Private",
    "state": "Punjab",
    "course": "MBBS",
    "counseling_route": "STATE",
    "quota_type": "Competent Authority Quota",
    "seats": 50,
    "seats_prev": 25,
    "seats_inc": 25,
    "pg_seats": 0,
    "ss_seats": 0
  },
  {
    "college_id": "ug_pb011p3",
    "college_name": "RIMT Medical College and Hospital",
    "college_type": "Private",
    "state": "Punjab",
    "course": "MBBS",
    "counseling_route": "STATE",
    "quota_type": "Management Quota",
    "seats": 35,
    "seats_prev": 17,
    "seats_inc": 17,
    "pg_seats": 0,
    "ss_seats": 0
  },
  {
    "college_id": "ug_pb011p3",
    "college_name": "RIMT Medical College and Hospital",
    "college_type": "Private",
    "state": "Punjab",
    "course": "MBBS",
    "counseling_route": "STATE",
    "quota_type": "NRI / Minority Quota",
    "seats": 15,
    "seats_prev": 8,
    "seats_inc": 8,
    "pg_seats": 0,
    "ss_seats": 0
  },
  {
    "college_id": "ug_pb012p3",
    "college_name": "Sri Guru Ram Das Institute of Medical Sciences and Research, Sri Amritsar",
    "college_type": "Private",
    "state": "Punjab",
    "course": "MBBS",
    "counseling_route": "STATE",
    "quota_type": "Competent Authority Quota",
    "seats": 75,
    "seats_prev": 75,
    "seats_inc": 0,
    "pg_seats": 139,
    "ss_seats": 0
  },
  {
    "college_id": "ug_pb012p3",
    "college_name": "Sri Guru Ram Das Institute of Medical Sciences and Research, Sri Amritsar",
    "college_type": "Private",
    "state": "Punjab",
    "course": "MBBS",
    "counseling_route": "STATE",
    "quota_type": "Management Quota",
    "seats": 52,
    "seats_prev": 52,
    "seats_inc": 0,
    "pg_seats": 139,
    "ss_seats": 0
  },
  {
    "college_id": "ug_pb012p3",
    "college_name": "Sri Guru Ram Das Institute of Medical Sciences and Research, Sri Amritsar",
    "college_type": "Private",
    "state": "Punjab",
    "course": "MBBS",
    "counseling_route": "STATE",
    "quota_type": "NRI / Minority Quota",
    "seats": 23,
    "seats_prev": 23,
    "seats_inc": 0,
    "pg_seats": 139,
    "ss_seats": 0
  }
]